purestemmer
