Metadata-Version: 1.1
Name: purestemmer
Version: 0.1.1
Summary: Pure-Python implementations of the Snowball stemmers
Home-page: https://github.com/torfuspolymorphus/purestemmer
Author: Florian Brucker
Author-email: mail@florianbrucker.de
License: ['MIT', 'BSD']
Keywords: python,information retrieval,language processing,morphological analysis,stemming algorithms,stemmers
Platform: any
Classifier: Development Status :: 4 - Beta
Classifier: Intended Audience :: Developers
Classifier: License :: OSI Approved :: MIT License
Classifier: License :: OSI Approved :: BSD License
Classifier: Natural Language :: Danish
Classifier: Natural Language :: Dutch
Classifier: Natural Language :: English
Classifier: Natural Language :: Finnish
Classifier: Natural Language :: French
Classifier: Natural Language :: German
Classifier: Natural Language :: Italian
Classifier: Natural Language :: Norwegian
Classifier: Natural Language :: Portuguese
Classifier: Natural Language :: Russian
Classifier: Natural Language :: Spanish
Classifier: Natural Language :: Swedish
Classifier: Operating System :: OS Independent
Classifier: Programming Language :: Python
Classifier: Programming Language :: Python :: 2
Classifier: Programming Language :: Python :: 2.7
Classifier: Topic :: Database
Classifier: Topic :: Internet :: WWW/HTTP :: Indexing/Search
Classifier: Topic :: Text Processing :: Indexing
Classifier: Topic :: Text Processing :: Linguistic
